pubmed_xml/__init__.py
pubmed_xml/version.json
pubmed_xml/bin/__init__.py
pubmed_xml/bin/main.py
pubmed_xml/core/__init__.py
pubmed_xml/core/abstract.py
pubmed_xml/core/article.py
pubmed_xml/core/parser.py
pubmed_xml/util/__init__.py
pubmed_xml-1.0.3.dist-info/METADATA
pubmed_xml-1.0.3.dist-info/WHEEL
pubmed_xml-1.0.3.dist-info/entry_points.txt
pubmed_xml-1.0.3.dist-info/top_level.txt
pubmed_xml-1.0.3.dist-info/RECORD
