Metadata-Version: 2.1
Name: pubmed-xml
Version: 1.0.3
Summary: Pubmed XML Parser
Home-page: https://github.com/suqingdong/pubmed_xml
Author: suqingdong
Author-email: suqingdong1114@gmail.com
License: MIT License
Platform: UNKNOWN
Classifier: Development Status :: 5 - Production/Stable
Classifier: Operating System :: OS Independent
Classifier: Intended Audience :: Developers
Classifier: License :: OSI Approved :: MIT License
Classifier: Programming Language :: Python
Classifier: Programming Language :: Python :: 3
Classifier: Programming Language :: Python :: 3.8
Classifier: Programming Language :: Python :: 3.9
Classifier: Topic :: Software Development :: Libraries
Requires-Dist: lxml
Requires-Dist: click
Requires-Dist: w3lib
Requires-Dist: requests
Requires-Dist: simple-loggers
